{
  "/docs-95e": {
    "__comp": "5e95c892",
    "__context": {
      "plugin": "aba21aa0"
    }
  },
  "/docs-22d": {
    "__comp": "a7bd4aaa",
    "__props": "0058b4c6"
  },
  "/docs-8af": {
    "__comp": "a94703ab"
  },
  "/docs/AUTHENTICATION_GUIDE-19f": {
    "__comp": "17896441",
    "content": "40067ae5"
  },
  "/docs/chapters/ch0-preface-4e7": {
    "__comp": "17896441",
    "content": "9b2eb954"
  },
  "/docs/chapters/ch0-prerequisites-f70": {
    "__comp": "17896441",
    "content": "a538877d"
  },
  "/docs/chapters/ch1-intro-cb6": {
    "__comp": "17896441",
    "content": "05fb7288"
  },
  "/docs/chapters/ch2-humanoid-80b": {
    "__comp": "17896441",
    "content": "40e36dd8"
  },
  "/docs/chapters/ch3-ros2-725": {
    "__comp": "17896441",
    "content": "ff802fd6"
  },
  "/docs/chapters/ch4-sim-a10": {
    "__comp": "17896441",
    "content": "3ea9cdb1"
  },
  "/docs/chapters/ch5-vla-342": {
    "__comp": "17896441",
    "content": "f1bf820f"
  },
  "/docs/chapters/ch6-capstone-1f9": {
    "__comp": "17896441",
    "content": "aa0a364f"
  },
  "/docs/modules/m1-ros2/m1-nodes-topics-services-a08": {
    "__comp": "17896441",
    "content": "ac085509"
  },
  "/docs/modules/m1-ros2/m1-overview-a25": {
    "__comp": "17896441",
    "content": "77891cf1"
  },
  "/docs/modules/m1-ros2/m1-python-agents-638": {
    "__comp": "17896441",
    "content": "2e2934d3"
  },
  "/docs/modules/m1-ros2/m1-urdf-humanoids-95f": {
    "__comp": "17896441",
    "content": "1a81998f"
  },
  "/docs/modules/m2-digital-twin/m2-gazebo-physics-5f1": {
    "__comp": "17896441",
    "content": "c09a8467"
  },
  "/docs/modules/m2-digital-twin/m2-overview-6d2": {
    "__comp": "17896441",
    "content": "5a1ec7c7"
  },
  "/docs/modules/m2-digital-twin/m2-sensor-simulation-7be": {
    "__comp": "17896441",
    "content": "df3667f8"
  },
  "/docs/modules/m2-digital-twin/m2-unity-rendering-00c": {
    "__comp": "17896441",
    "content": "2ce9ba0b"
  },
  "/docs/modules/m3-isaac/m3-isaac-ros-3c6": {
    "__comp": "17896441",
    "content": "1cb5aad3"
  },
  "/docs/modules/m3-isaac/m3-isaac-sim-591": {
    "__comp": "17896441",
    "content": "b7d7060e"
  },
  "/docs/modules/m3-isaac/m3-nav2-planning-4b8": {
    "__comp": "17896441",
    "content": "a98ed005"
  },
  "/docs/modules/m3-isaac/m3-overview-567": {
    "__comp": "17896441",
    "content": "41842554"
  },
  "/docs/modules/m4-vla/m4-capstone-project-423": {
    "__comp": "17896441",
    "content": "bee19bf6"
  },
  "/docs/modules/m4-vla/m4-cognitive-planning-ec4": {
    "__comp": "17896441",
    "content": "8f39cc56"
  },
  "/docs/modules/m4-vla/m4-overview-72c": {
    "__comp": "17896441",
    "content": "58027790"
  },
  "/docs/modules/m4-vla/m4-voice-to-action-f22": {
    "__comp": "17896441",
    "content": "8a0de893"
  },
  "/-2e1": {
    "__comp": "c4f5d8e4",
    "__context": {
      "plugin": "a7456010"
    },
    "config": "5e9f5e1a"
  }
}